[
  {
    "PK": "Regimen-Matt-Welte-MemberId",
    "MemberId": "Matt-Welte-MemberId",
    "RegimenId": "efb80c51-3367-4080-8339-af8107415cf1",
    "RegimenName": "My First Regimen",
    "Difficulty": 2,
    "RegimenDescription": "A 2 week test regimen",
    "StartDate": "2022-03-06T08:00:00+00:00",
    "EndDate": "2022-03-19T07:00:00+00:00",
    "Workouts": [
      {
        "WorkoutId": "d844b0fd-083d-4633-8274-18311c2d1370",
        "WorkoutName": "First Workout"
      },
      {
        "WorkoutId": "d844b0fd-083d-4633-8274-18311c2d1370",
        "WorkoutName": "First Workout"
      },
      {
        "WorkoutId": "d844b0fd-083d-4633-8274-18311c2d1370",
        "WorkoutName": "First Workout"
      }
    ],
    "MuscleSpecificity": 1,
    "Id": "efb80c51-3367-4080-8339-af8107415cf1",
    "Type": "Regimen",
    "ModifiedOn": "2022-03-06T22:59:33.9784058+00:00"
  }
]